dryml/__init__.py
dryml/collections.py
dryml/config.py
dryml/file_intermediary.py
dryml/object.py
dryml/repo.py
dryml/save_cache.py
dryml/selector.py
dryml/utils.py
dryml/workshop.py
dryml/context/__init__.py
dryml/context/context_tracker.py
dryml/context/process.py
dryml/context/tf/__init__.py
dryml/context/tf/context.py
dryml/context/torch/__init__.py
dryml/context/torch/context.py
dryml/data/__init__.py
dryml/data/dataset.py
dryml/data/image.py
dryml/data/numpy_dataset.py
dryml/data/transforms.py
dryml/data/util.py
dryml/data/pandas/__init__.py
dryml/data/pandas/prep_funcs.py
dryml/data/tf/__init__.py
dryml/data/tf/dataset.py
dryml/data/torch/__init__.py
dryml/data/torch/dataset.py
dryml/data/torch/transforms.py
dryml/metrics/__init__.py
dryml/metrics/scalar.py
dryml/models/__init__.py
dryml/models/component.py
dryml/models/model.py
dryml/models/pipe.py
dryml/models/train_spec.py
dryml/models/trainable.py
dryml/models/utils.py
dryml/models/sklearn/__init__.py
dryml/models/sklearn/base.py
dryml/models/tf/__init__.py
dryml/models/tf/base.py
dryml/models/tf/utils.py
dryml/models/tf/keras/__init__.py
dryml/models/tf/keras/base.py
dryml/models/torch/__init__.py
dryml/models/torch/base.py
dryml/models/torch/generic.py
dryml/models/xgb/__init__.py
dryml/models/xgb/base.py
dryml/ray/__init__.py
dryml/ray/tune.py
dryml/vis/__init__.py
dryml/vis/scalar.py
dryml-0.2.2.dist-info/LICENSE
dryml-0.2.2.dist-info/METADATA
dryml-0.2.2.dist-info/WHEEL
dryml-0.2.2.dist-info/top_level.txt
dryml-0.2.2.dist-info/RECORD
