Metadata-Version: 2.1
Name: dryml
Version: 0.2.2
Summary: Don't Repeat Yourself Machine Learning: A Machine Learning library to reduce code duplication, and increase portability and interoperability in the Machine Learning Space.
Home-page: https://github.com/ncsa/dryml
Author: Matthew Krafczyk
Author-email: mkrafcz2@illinois.edu
License: Apache-2.0
Project-URL: homepage, https://github.com/ncsa/dryml
Project-URL: Bug Tracker, https://github.com/ncsa/dryml/issues
Keywords: ML
Classifier: Programming Language :: Python :: 3
Classifier: License :: OSI Approved :: Apache Software License
Classifier: Operating System :: OS Independent
Classifier: Development Status :: 4 - Beta
Classifier: Intended Audience :: Developers
Classifier: Intended Audience :: Science/Research
Classifier: Topic :: Scientific/Engineering
Classifier: Topic :: Scientific/Engineering :: Artificial Intelligence
Classifier: Topic :: Software Development
Classifier: Topic :: Software Development :: Libraries
Classifier: Topic :: Software Development :: Libraries :: Application Frameworks
Classifier: Topic :: Software Development :: Libraries :: Python Modules
Requires-Python: >=3.7
License-File: LICENSE
Requires-Dist: dill
Requires-Dist: tqdm
Requires-Dist: numpy
Requires-Dist: gputil
Provides-Extra: ray
Requires-Dist: ray-core; extra == "ray"
Requires-Dist: ray-tune; extra == "ray"
Provides-Extra: sklearn
Requires-Dist: scikit-learn; extra == "sklearn"
Provides-Extra: test
Requires-Dist: pytest; extra == "test"
Requires-Dist: pytest-cov; extra == "test"
Requires-Dist: flake8; extra == "test"
Provides-Extra: tf
Requires-Dist: tensorflow; extra == "tf"
Provides-Extra: torch
Requires-Dist: pytorch; extra == "torch"
Provides-Extra: xgboost
Requires-Dist: scikit-learn; extra == "xgboost"
Requires-Dist: xgboost; extra == "xgboost"
